MANIFEST.in
README.txt
setup.py
Select_Shuttle.egg-info/CHANGELOG.txt
Select_Shuttle.egg-info/LICENSE.optiontransfer
Select_Shuttle.egg-info/PKG-INFO
Select_Shuttle.egg-info/README.txt
Select_Shuttle.egg-info/SOURCES.txt
Select_Shuttle.egg-info/dependency_links.txt
Select_Shuttle.egg-info/entry_points.txt
Select_Shuttle.egg-info/not-zip-safe
Select_Shuttle.egg-info/paster_plugins.txt
Select_Shuttle.egg-info/requires.txt
Select_Shuttle.egg-info/sqlobject.txt
Select_Shuttle.egg-info/top_level.txt
selectshuttle/__init__.py
selectshuttle/release.py
selectshuttle/widgets.py
selectshuttle/static/javascript/OptionTransfer.js